{
  "entries": [
    {
      "id": 0,
      "templateTwi": "Me pɛ sɛ me nom ___.",
      "missingTwi": "nsuo",
      "translationDutch": "Ik drink graag water.",
      "audioclip": "test.mp3"
    },
    {
      "id": 1,
      "templateTwi": "Ɔkyena me kɔ ___.",
      "missingTwi": "adwuma",
      "translationDutch": "Morgen ga ik naar het werk.",
      "audioclip": "test.mp3"
    },
    {
      "id": 2,
      "templateTwi": "Me pɛ sɛ me di ___.",
      "missingTwi": "aduane",
      "translationDutch": "Ik wil eten.",
      "audioclip": "test.mp3"
    },
    {
      "id": 3,
      "templateTwi": "Wo ___ yɛ fɛ paa.",
      "missingTwi": "fie",
      "translationDutch": "Jouw huis is erg mooi.",
      "audioclip": "test.mp3"
    },
    {
      "id": 4,
      "templateTwi": "___ no hyerɛn.",
      "missingTwi": "ɛwia",
      "translationDutch": "De zon schijnt.",
      "audioclip": "test.mp3"
    },
    {
      "id": 5,
      "templateTwi": "Kofi ɛ fa ___ mu.",
      "missingTwi": "ɔpono",
      "translationDutch": "Kofi gaat door de deur.",
      "audioclip": "test.mp3"
    },
    {
      "id": 6,
      "templateTwi": "Ɛdua no yɛ ___.",
      "missingTwi": "kɛse",
      "translationDutch": "De boom is groot.",
      "audioclip": "test.mp3"
    },
    {
      "id": 7,
      "templateTwi": "Me ba no yɛ ___.",
      "missingTwi": "ketewa",
      "translationDutch": "Mijn kind is klein.",
      "audioclip": "test.mp3"
    },
    {
      "id": 8,
      "templateTwi": "Seesei me reba ___.",
      "missingTwi": "efie",
      "translationDutch": "Nu kom ik naar huis.",
      "audioclip": "test.mp3"
    },
    {
      "id": 9,
      "templateTwi": "Me di ___ Anɔpa .",
      "missingTwi": "aduane",
      "translationDutch": "Ik eet in de ochtend.",
      "audioclip": "test.mp3"
    },
    {
      "id": 10,
      "templateTwi": "Agoo, ___ ha.",
      "missingTwi": "bra",
      "translationDutch": "Hallo, kom hier.",
      "audioclip": "test.mp3"
    },
    {
      "id": 11,
      "templateTwi": "Ɛpono no mu yɛ ___.",
      "missingTwi": "tuntum",
      "translationDutch": "De deur is zwart.",
      "audioclip": "test.mp3"
    },
    {
      "id": 12,
      "templateTwi": "Me ___ no yɛ nnam paa.",
      "missingTwi": "sekan",
      "translationDutch": "Mijn zwaard is erg scherp.",
      "audioclip": "test.mp3"
    },
    {
      "id": 13,
      "templateTwi": "Maame ____ aduanɛ.",
      "missingTwi": "nua",
      "translationDutch": "Moeder kookt eten.",
      "audioclip": "test.mp3"
    },
    {
      "id": 14,
      "templateTwi": "Dua no ___.",
      "missingTwi": "gyena hɔ",
      "translationDutch": "De boom staat daar.",
      "audioclip": "test.mp3"
    },
    {
      "id": 15,
      "templateTwi": "Abɔfra no e'di ___.",
      "missingTwi": "agorɔ",
      "translationDutch": "Het kind speelt.",
      "audioclip": "test.mp3"
    },
    {
      "id": 16,
      "templateTwi": "Me onuabaa na ɛhwɛ ___.",
      "missingTwi": "me",
      "translationDutch": "Mijn zus zorgt voor mij.",
      "audioclip": "test.mp3"
    },
    {
      "id": 17,
      "templateTwi": "Me papa na ɛ ___ me.",
      "missingTwi": "kyerɛ",
      "translationDutch": "Vader leert mij.",
      "audioclip": "test.mp3"
    },
        {
      "id": 18,
      "templateTwi": "Wo pɛ ___?",
      "missingTwi": "aduane",
      "translationDutch": "Wil jij eten?",
      "audioclip": "test.mp3"
    },
    {
      "id": 19,
      "templateTwi": "Aane, me pɛ ___.",
      "missingTwi": "nsuo",
      "translationDutch": "Ja, ik wil water.",
      "audioclip": "test.mp3"
    },
    {
      "id": 20,
      "templateTwi": "Abofra no ___.",
      "missingTwi": "ada",
      "translationDutch": "Het kind slaapt.",
      "audioclip": "test.mp3"
    },
    {
      "id": 21,
      "templateTwi": "___ no a sɔ.",
      "missingTwi": "Egya",
      "translationDutch": "Het vuur is aan.",
      "audioclip": "test.mp3"
    },
    {
      "id": 22,
      "templateTwi": "Bue ___ no.",
      "missingTwi": "ɛpono",
      "translationDutch": "Doe de deur open.",
      "audioclip": "test.mp3"
    },
    {
      "id": 23,
      "templateTwi": "Mete ___ hɔ.",
      "missingTwi": "eFie",
      "translationDutch": "Ik woon in die huis.",
      "audioclip": "test.mp3"
    },
    {
      "id": 24,
      "templateTwi": "Seesei me kɔ ___.",
      "missingTwi": "adwuma",
      "translationDutch": "Ik ga nu naar werk.",
      "audioclip": "test.mp3"
    },
    {
      "id": 25,
      "templateTwi": "Me kan efri baako a kosi ___.",
      "missingTwi": "edu",
      "translationDutch": "Ik tel van één tot tien.",
      "audioclip": "test.mp3"
    }
]
}